sert/__init__.py
sert/losses.py
sert/_experimental/__init__.py
sert/_experimental/_sert.py
sert/datasets/__init__.py
sert/datasets/simulate_timeseries.py
sert/datasets/timeseries_classification.py
sert/models/__init__.py
sert/models/_custom_layers.py
sert/models/sernn.py
sert/models/sert.py
sert/preprocessing/__init__.py
sert/preprocessing/sequential.py
sert/preprocessing/static.py
sert-0.0.1.dist-info/METADATA
sert-0.0.1.dist-info/WHEEL
sert-0.0.1.dist-info/licenses/LICENSE
sert-0.0.1.dist-info/RECORD
