Metadata-Version: 2.1
Name: sert
Version: 0.0.1
Summary: SERT Python Package
Author-email: Amin Shoari Nejad <amin.shoarinejad@gmail.com>
License: Apache License
License-File: LICENSE
Classifier: Development Status :: 2 - Pre-Alpha
Classifier: Intended Audience :: Developers
Classifier: Natural Language :: English
Classifier: Programming Language :: Python :: 3
Classifier: Programming Language :: Python :: 3.6
Classifier: Programming Language :: Python :: 3.7
Classifier: Programming Language :: Python :: 3.8
Requires-Python: >=3.5
Requires-Dist: keras-nlp>=0.6.0
Requires-Dist: numpy
Requires-Dist: pandas
Requires-Dist: tensorflow>=2.0.0
